nlpiper/__init__.py
nlpiper/core/__init__.py
nlpiper/core/composition.py
nlpiper/core/document.py
nlpiper/logger.py
nlpiper/transformers/__init__.py
nlpiper/transformers/base.py
nlpiper/transformers/cleaners.py
nlpiper/transformers/embeddings.py
nlpiper/transformers/normalizers.py
nlpiper/transformers/tokenizers.py
nlpiper-0.3.1.dist-info/LICENSE
nlpiper-0.3.1.dist-info/WHEEL
nlpiper-0.3.1.dist-info/METADATA
nlpiper-0.3.1.dist-info/RECORD
