Metadata-Version: 2.1
Name: nlpiper
Version: 0.3.1
Summary: NLPiper, a lightweight package integrated with a universe of frameworks to pre-process documents.
Home-page: https://github.com/dlite-tools/NLPiper
License: MIT
Keywords: NLP,CL,natural language processing,computational linguistics,parsing,tokenizing,linguistics,language,natural language,text analytics,deep-learning 
Author: Tomás Osório
Maintainer: Carlos Alves, Daniel Ferrari, João Cunha, Tomás Osório
Requires-Python: >=3.7,<4.0
Classifier: Development Status :: 4 - Beta
Classifier: Intended Audience :: Developers
Classifier: License :: Freely Distributable
Classifier: License :: OSI Approved :: MIT License
Classifier: Natural Language :: English
Classifier: Programming Language :: Python :: 3
Classifier: Programming Language :: Python :: 3.10
Classifier: Programming Language :: Python :: 3.7
Classifier: Programming Language :: Python :: 3.8
Classifier: Programming Language :: Python :: 3.9
Classifier: Topic :: Software Development :: Libraries :: Python Modules
Classifier: Topic :: Utilities
Provides-Extra: all
Provides-Extra: bs4
Provides-Extra: gensim
Provides-Extra: hunspell
Provides-Extra: nltk
Provides-Extra: numpy
Provides-Extra: sacremoses
Provides-Extra: spacy
Provides-Extra: stanza
Provides-Extra: torchtext
Requires-Dist: bs4 (>=0,<1); extra == "bs4" or extra == "all"
Requires-Dist: cyhunspell (>=2,<3); extra == "hunspell" or extra == "all"
Requires-Dist: gensim (>=4,<5); extra == "gensim" or extra == "all"
Requires-Dist: nltk (>=3,<4); extra == "nltk" or extra == "all"
Requires-Dist: numpy (>=1,<2); extra == "numpy" or extra == "all"
Requires-Dist: pydantic (>=1,<2)
Requires-Dist: sacremoses (>=0,<1); extra == "sacremoses" or extra == "all"
Requires-Dist: spacy (>=3,<4); extra == "spacy" or extra == "all"
Requires-Dist: stanza (>=1,<2); extra == "stanza" or extra == "all"
Requires-Dist: torchtext (>=0,<1); extra == "torchtext" or extra == "all"
Project-URL: Documentation, https://github.com/dlite-tools/NLPiper/README.md
Project-URL: Repository, https://github.com/dlite-tools/NLPiper
